bikemi_unofficial_api/__init__.py
bikemi_unofficial_api/bikemi.py
BikeMi_unofficial_API-1.0.2.dist-info/LICENSE.txt
BikeMi_unofficial_API-1.0.2.dist-info/METADATA
BikeMi_unofficial_API-1.0.2.dist-info/WHEEL
BikeMi_unofficial_API-1.0.2.dist-info/top_level.txt
BikeMi_unofficial_API-1.0.2.dist-info/RECORD
